{
  "aliases": [
  ],
  "bottle": {
    "stable": {
      "cellar": "/home/linuxbrew/.linuxbrew/Cellar",
      "files": {
        "el_capitan": {
          "sha256": "a3385e12f96372323504cf50f32b7a045a24e90d0b767ed9be98fdf705d4d65b",
          "url": "https://linuxbrew.bintray.com/bottles/alpine-2.21.el_capitan.bottle.1.tar.gz"
        },
        "high_sierra": {
          "sha256": "86c4bb588e6c99a856b665d7643cf8ad699c9add68f7301db804085533480cd8",
          "url": "https://linuxbrew.bintray.com/bottles/alpine-2.21.high_sierra.bottle.1.tar.gz"
        },
        "sierra": {
          "sha256": "8d0c2b6cd5b91cb904f1ddebe8b5ba27f1c2db50fe26db9a40a8131943abe2b5",
          "url": "https://linuxbrew.bintray.com/bottles/alpine-2.21.sierra.bottle.1.tar.gz"
        },
        "yosemite": {
          "sha256": "5b57214d7c4603dea4081f4aa8edee42c148a7daad1ed1fd881d4fb01a28d778",
          "url": "https://linuxbrew.bintray.com/bottles/alpine-2.21.yosemite.bottle.1.tar.gz"
        }
      },
      "prefix": "/home/linuxbrew/.linuxbrew",
      "rebuild": 1,
      "root_url": "https://linuxbrew.bintray.com/bottles"
    }
  },
  "build_dependencies": [
  ],
  "caveats": null,
  "conflicts_with": [
  ],
  "dependencies": [
    "openssl"
  ],
  "desc": "News and email agent",
  "full_name": "alpine",
  "homepage": "http://repo.or.cz/alpine.git",
  "installed": [
  ],
  "keg_only": false,
  "linked_keg": null,
  "name": "alpine",
  "oldname": null,
  "optional_dependencies": [
  ],
  "options": [
  ],
  "outdated": false,
  "pinned": false,
  "recommended_dependencies": [
  ],
  "requirements": [
  ],
  "revision": 0,
  "version_scheme": 0,
  "versions": {
    "bottle": true,
    "devel": null,
    "head": null,
    "stable": "2.21"
  }
}