{"name":"binaryen","full_name":"binaryen","desc":"Compiler infrastructure and toolchain library for WebAssembly","homepage":"http://webassembly.org/","oldname":null,"aliases":[],"versions":{"stable":"46","bottle":true,"devel":null,"head":"HEAD"},"revision":0,"version_scheme":0,"installed":[],"linked_keg":null,"pinned":false,"outdated":false,"keg_only":false,"dependencies":["cmake"],"recommended_dependencies":[],"optional_dependencies":[],"build_dependencies":["cmake"],"conflicts_with":[],"caveats":null,"requirements":[{"name":"macos","cask":null,"download":null}],"options":[],"bottle":{"stable":{"rebuild":0,"cellar":":any","prefix":"/usr/local","root_url":"https://homebrew.bintray.com/bottles","files":{"high_sierra":{"url":"https://homebrew.bintray.com/bottles/binaryen-46.high_sierra.bottle.tar.gz","sha256":"f6a91d62394f7c2949259168832a0b4db8ace7974f2bb3fb288ef6c95c902b77"},"sierra":{"url":"https://homebrew.bintray.com/bottles/binaryen-46.sierra.bottle.tar.gz","sha256":"61dac3952af1e00ed86c78f85d84d6ad400baf6f3349ebf58fb667e149fe592a"},"el_capitan":{"url":"https://homebrew.bintray.com/bottles/binaryen-46.el_capitan.bottle.tar.gz","sha256":"bd434cd5c3915801b207dc66250a6a7db48b95534e112f124725c46c6bbcfd00"}}}}}