{"name":"blockhash","full_name":"blockhash","desc":"Perceptual image hash calculation tool","homepage":"https://github.com/commonsmachinery/blockhash","oldname":null,"aliases":[],"versions":{"stable":"0.3","bottle":true,"devel":null,"head":"HEAD"},"revision":1,"version_scheme":0,"installed":[],"linked_keg":null,"pinned":false,"outdated":false,"keg_only":false,"dependencies":["pkg-config","imagemagick"],"recommended_dependencies":[],"optional_dependencies":[],"build_dependencies":["pkg-config"],"conflicts_with":[],"caveats":null,"requirements":[],"options":[],"bottle":{"stable":{"rebuild":0,"cellar":":any","prefix":"/usr/local","root_url":"https://homebrew.bintray.com/bottles","files":{"high_sierra":{"url":"https://homebrew.bintray.com/bottles/blockhash-0.3_1.high_sierra.bottle.tar.gz","sha256":"d93acc3ec087d317d7e0fbe166d83745f516d2f85d32c3acc8fa0a18b764853c"},"sierra":{"url":"https://homebrew.bintray.com/bottles/blockhash-0.3_1.sierra.bottle.tar.gz","sha256":"e4cce87334c21ede18f40f74ccb2f00a9d298e3b4f4e46b4aaedeefe0341e95e"},"el_capitan":{"url":"https://homebrew.bintray.com/bottles/blockhash-0.3_1.el_capitan.bottle.tar.gz","sha256":"41faab24b6b7e72dff9719972dd7c2fc16864c2b99a69aa5d6250816b27aa2e3"}}}}}