{
  "aliases": [
  ],
  "bottle": {
    "stable": {
      "cellar": "/home/linuxbrew/.linuxbrew/Cellar",
      "files": {
        "el_capitan": {
          "sha256": "0de1a4dbee4c5b0b0a50279ac288f3b0d9263739f7ea440d0db5402c843139d4",
          "url": "https://linuxbrew.bintray.com/bottles/botan-2.6.0.el_capitan.bottle.tar.gz"
        },
        "high_sierra": {
          "sha256": "5c173d12f563c782ea7f66b334b83202e5e07401ca11eb4b3f991f06b168a262",
          "url": "https://linuxbrew.bintray.com/bottles/botan-2.6.0.high_sierra.bottle.tar.gz"
        },
        "sierra": {
          "sha256": "81697f0f4796105afbe523422505180d8192576495e841e39f1fd645c0a39002",
          "url": "https://linuxbrew.bintray.com/bottles/botan-2.6.0.sierra.bottle.tar.gz"
        }
      },
      "prefix": "/home/linuxbrew/.linuxbrew",
      "rebuild": 0,
      "root_url": "https://linuxbrew.bintray.com/bottles"
    }
  },
  "build_dependencies": [
    "pkg-config"
  ],
  "caveats": null,
  "conflicts_with": [
  ],
  "dependencies": [
    "pkg-config",
    "openssl"
  ],
  "desc": "Cryptographic algorithms and formats library in C++",
  "full_name": "botan",
  "homepage": "https://botan.randombit.net/",
  "installed": [
  ],
  "keg_only": false,
  "linked_keg": null,
  "name": "botan",
  "oldname": null,
  "optional_dependencies": [
  ],
  "options": [
    {
      "description": "Enable debug build of Botan",
      "option": "--with-debug"
    }
  ],
  "outdated": false,
  "pinned": false,
  "recommended_dependencies": [
  ],
  "requirements": [
  ],
  "revision": 0,
  "version_scheme": 0,
  "versions": {
    "bottle": true,
    "devel": null,
    "head": "HEAD",
    "stable": "2.6.0"
  }
}