{"name":"check_postgres","full_name":"check_postgres","desc":"Monitor Postgres databases","homepage":"https://bucardo.org/wiki/Check_postgres","oldname":null,"aliases":[],"versions":{"stable":"2.22.0","bottle":true,"devel":null,"head":"HEAD"},"revision":3,"version_scheme":0,"installed":[],"linked_keg":null,"pinned":false,"outdated":false,"keg_only":false,"dependencies":["postgresql"],"recommended_dependencies":[],"optional_dependencies":[],"build_dependencies":[],"conflicts_with":[],"caveats":null,"requirements":[],"options":[],"bottle":{"stable":{"rebuild":0,"cellar":":any_skip_relocation","prefix":"/usr/local","root_url":"https://homebrew.bintray.com/bottles","files":{"high_sierra":{"url":"https://homebrew.bintray.com/bottles/check_postgres-2.22.0_3.high_sierra.bottle.tar.gz","sha256":"2cca947a07f41712768a1f50a7fcbabcb35d8585c5faf4564e6470181ff6d786"},"sierra":{"url":"https://homebrew.bintray.com/bottles/check_postgres-2.22.0_3.sierra.bottle.tar.gz","sha256":"2cca947a07f41712768a1f50a7fcbabcb35d8585c5faf4564e6470181ff6d786"},"el_capitan":{"url":"https://homebrew.bintray.com/bottles/check_postgres-2.22.0_3.el_capitan.bottle.tar.gz","sha256":"2cca947a07f41712768a1f50a7fcbabcb35d8585c5faf4564e6470181ff6d786"}}}}}