{
  "aliases": [
  ],
  "bottle": {
    "stable": {
      "cellar": ":any_skip_relocation",
      "files": {
        "el_capitan": {
          "sha256": "0af8a184c2790eacbd3e0b43e90a55fc15baf17ba1f4963c5b05f78b7785737c",
          "url": "https://linuxbrew.bintray.com/bottles/honcho-1.0.1.el_capitan.bottle.tar.gz"
        },
        "high_sierra": {
          "sha256": "c0f694652d43aa7baefb6ef0a45817e4c5e5f68ca2eb4a54424b7f3fbcfb07b3",
          "url": "https://linuxbrew.bintray.com/bottles/honcho-1.0.1.high_sierra.bottle.tar.gz"
        },
        "sierra": {
          "sha256": "cd5b5d510c350dbc1780bddb82760603ebcacbb2dd382955f2a9f4b781e02005",
          "url": "https://linuxbrew.bintray.com/bottles/honcho-1.0.1.sierra.bottle.tar.gz"
        },
        "yosemite": {
          "sha256": "0af8a184c2790eacbd3e0b43e90a55fc15baf17ba1f4963c5b05f78b7785737c",
          "url": "https://linuxbrew.bintray.com/bottles/honcho-1.0.1.yosemite.bottle.tar.gz"
        }
      },
      "prefix": "/home/linuxbrew/.linuxbrew",
      "rebuild": 0,
      "root_url": "https://linuxbrew.bintray.com/bottles"
    }
  },
  "build_dependencies": [
  ],
  "caveats": null,
  "conflicts_with": [
  ],
  "dependencies": [
    "python@2"
  ],
  "desc": "Python clone of Foreman, for managing Procfile-based applications",
  "full_name": "honcho",
  "homepage": "https://github.com/nickstenning/honcho",
  "installed": [
  ],
  "keg_only": false,
  "linked_keg": null,
  "name": "honcho",
  "oldname": null,
  "optional_dependencies": [
  ],
  "options": [
  ],
  "outdated": false,
  "pinned": false,
  "recommended_dependencies": [
  ],
  "requirements": [
  ],
  "revision": 0,
  "version_scheme": 0,
  "versions": {
    "bottle": true,
    "devel": null,
    "head": null,
    "stable": "1.0.1"
  }
}