{"name":"json-fortran","full_name":"json-fortran","desc":"Fortran 2008 JSON API","homepage":"https://github.com/jacobwilliams/json-fortran","oldname":null,"aliases":[],"versions":{"stable":"6.2.0","bottle":true,"devel":null,"head":"HEAD"},"revision":0,"version_scheme":0,"installed":[],"linked_keg":null,"pinned":false,"outdated":false,"keg_only":false,"dependencies":["cmake","ford","gcc"],"recommended_dependencies":[],"optional_dependencies":[],"build_dependencies":["cmake","ford"],"conflicts_with":[],"caveats":null,"requirements":[],"options":[{"option":"--with-unicode-support","description":"Build json-fortran to support unicode text in json objects and files"},{"option":"--without-docs","description":"Do not build and install FORD generated documentation for json-fortran"}],"bottle":{"stable":{"rebuild":0,"cellar":":any","prefix":"/usr/local","root_url":"https://homebrew.bintray.com/bottles","files":{"high_sierra":{"url":"https://homebrew.bintray.com/bottles/json-fortran-6.2.0.high_sierra.bottle.tar.gz","sha256":"e016f9be8526b327654efd35fcceaf2c67a527111506ef31dff7e8d052f5e154"},"sierra":{"url":"https://homebrew.bintray.com/bottles/json-fortran-6.2.0.sierra.bottle.tar.gz","sha256":"11d23e9f8ec4643eb9ba2c76ac92160208efc3d897f9bedd11a4694d4f20eb40"},"el_capitan":{"url":"https://homebrew.bintray.com/bottles/json-fortran-6.2.0.el_capitan.bottle.tar.gz","sha256":"4850076213f1073611bd6f77e907853972fe2ac851880086d254149910d35c48"}}}}}