{"name":"moc","full_name":"moc","desc":"Terminal-based music player","homepage":"https://moc.daper.net/","oldname":null,"aliases":[],"versions":{"stable":"2.5.2","bottle":true,"devel":"2.6-alpha3","head":"HEAD"},"revision":2,"version_scheme":0,"installed":[],"linked_keg":null,"pinned":false,"outdated":false,"keg_only":false,"dependencies":["pkg-config","berkeley-db","ffmpeg","jack","libtool","ncurses"],"recommended_dependencies":[],"optional_dependencies":[],"build_dependencies":["pkg-config"],"conflicts_with":[],"caveats":"You must start the jack daemon prior to running mocp.\nIf you need wide-character support in the player, for example\nwith Chinese characters, you can install using\n    --with-ncurses\n","requirements":[],"options":[],"bottle":{"stable":{"rebuild":1,"cellar":"/usr/local/Cellar","prefix":"/usr/local","root_url":"https://homebrew.bintray.com/bottles","files":{"high_sierra":{"url":"https://homebrew.bintray.com/bottles/moc-2.5.2_2.high_sierra.bottle.1.tar.gz","sha256":"fbabdaaaea2215a4b20636cf32f0fcf1723dbbfe3c522448c1d9bd4057ee8a7e"},"sierra":{"url":"https://homebrew.bintray.com/bottles/moc-2.5.2_2.sierra.bottle.1.tar.gz","sha256":"785c68d5b1657c4bd9cd5a28bf0a1707cad2e7c3b822e1571871cb42464f4844"},"el_capitan":{"url":"https://homebrew.bintray.com/bottles/moc-2.5.2_2.el_capitan.bottle.1.tar.gz","sha256":"09e0d32b7feaf0fc50e1cfe52a0692c5e514ea3f22463becd47b94a001cb8bcd"}}}}}