{"name":"pianobar","full_name":"pianobar","desc":"Command-line player for https://pandora.com","homepage":"https://github.com/PromyLOPh/pianobar/","oldname":null,"aliases":[],"versions":{"stable":"2017.08.30","bottle":true,"devel":null,"head":"HEAD"},"revision":0,"version_scheme":0,"installed":[],"linked_keg":null,"pinned":false,"outdated":false,"keg_only":false,"dependencies":["pkg-config","libao","mad","faad2","gnutls","libgcrypt","json-c","ffmpeg"],"recommended_dependencies":[],"optional_dependencies":[],"build_dependencies":["pkg-config"],"conflicts_with":[],"caveats":null,"requirements":[],"options":[],"bottle":{"stable":{"rebuild":0,"cellar":":any","prefix":"/usr/local","root_url":"https://homebrew.bintray.com/bottles","files":{"high_sierra":{"url":"https://homebrew.bintray.com/bottles/pianobar-2017.08.30.high_sierra.bottle.tar.gz","sha256":"e4d59eee9e6d6d6b78b5bd2541a7faa23beda9edbe9179678cb46ca006e616f0"},"sierra":{"url":"https://homebrew.bintray.com/bottles/pianobar-2017.08.30.sierra.bottle.tar.gz","sha256":"327b53a2b9e2fd6824d0c854b5ea411b29b07ba5804b443c453aee05a86e36d4"},"el_capitan":{"url":"https://homebrew.bintray.com/bottles/pianobar-2017.08.30.el_capitan.bottle.tar.gz","sha256":"ea582da39bf90a0122d74678cdf82349af53adcbab48ff5bd2d57c64ca16150f"},"yosemite":{"url":"https://homebrew.bintray.com/bottles/pianobar-2017.08.30.yosemite.bottle.tar.gz","sha256":"41d44c9f1680fa404639ae9b907df30bbb019b1628454e8d77eba95af6a1a883"}}}}}