{
  "aliases": [
    "postgres",
    "postgresql@10"
  ],
  "bottle": {
    "stable": {
      "cellar": "/home/linuxbrew/.linuxbrew/Cellar",
      "files": {
        "el_capitan": {
          "sha256": "0581e9efe089864abbcc938f70a5175ff5595ffd701062bafec0be041ba56258",
          "url": "https://linuxbrew.bintray.com/bottles/postgresql-10.3.el_capitan.bottle.tar.gz"
        },
        "high_sierra": {
          "sha256": "632a988ae9a6b45acd3fca3f05af7dbec02e01fa91814ff8ba238cc20d1a7f38",
          "url": "https://linuxbrew.bintray.com/bottles/postgresql-10.3.high_sierra.bottle.tar.gz"
        },
        "sierra": {
          "sha256": "c5412eb34006856a6f0aca2ca2c69e2b8da706f1c6a6aae200aa81d0cda23207",
          "url": "https://linuxbrew.bintray.com/bottles/postgresql-10.3.sierra.bottle.tar.gz"
        },
        "x86_64_linux": {
          "sha256": "46a405f14a0cc60d60fefa5d3f99afb2e1cf708d3bb7c60803fbb8f147292987",
          "url": "https://linuxbrew.bintray.com/bottles/postgresql-10.3.x86_64_linux.bottle.tar.gz"
        }
      },
      "prefix": "/home/linuxbrew/.linuxbrew",
      "rebuild": 0,
      "root_url": "https://linuxbrew.bintray.com/bottles"
    }
  },
  "build_dependencies": [
  ],
  "caveats": "To migrate existing data from a previous major version of PostgreSQL run:\n  brew postgresql-upgrade-database\n",
  "conflicts_with": [
    "postgres-xc"
  ],
  "dependencies": [
    "openssl",
    "readline",
    "python",
    "python@2",
    "libxslt",
    "perl",
    "util-linux"
  ],
  "desc": "Object-relational database system",
  "full_name": "postgresql",
  "homepage": "https://www.postgresql.org/",
  "installed": [
  ],
  "keg_only": false,
  "linked_keg": null,
  "name": "postgresql",
  "oldname": null,
  "optional_dependencies": [
    "python",
    "python@2"
  ],
  "options": [
    {
      "description": "Build without Perl support",
      "option": "--without-perl"
    },
    {
      "description": "Build with Tcl support",
      "option": "--with-tcl"
    },
    {
      "description": "Build with DTrace support",
      "option": "--with-dtrace"
    },
    {
      "description": "Enable PL/Python3 (incompatible with --with-python@2)",
      "option": "--with-python"
    },
    {
      "description": "Enable PL/Python2",
      "option": "--with-python@2"
    }
  ],
  "outdated": false,
  "pinned": false,
  "recommended_dependencies": [
    "perl"
  ],
  "requirements": [
  ],
  "revision": 0,
  "version_scheme": 0,
  "versions": {
    "bottle": true,
    "devel": null,
    "head": "HEAD",
    "stable": "10.3"
  }
}