{
  "aliases": [
  ],
  "bottle": {
    "stable": {
      "cellar": ":any",
      "files": {
        "el_capitan": {
          "sha256": "4aa50d19fa164c7bb5b6a14f5ef562fb9b40acebe8575cd5af4dffac78fa3400",
          "url": "https://linuxbrew.bintray.com/bottles/privoxy-3.0.26.el_capitan.bottle.1.tar.gz"
        },
        "high_sierra": {
          "sha256": "6d73d0568bf02dc31bce3e87a92ed8a90c67d19340ecbc2d22102522dc12a74b",
          "url": "https://linuxbrew.bintray.com/bottles/privoxy-3.0.26.high_sierra.bottle.1.tar.gz"
        },
        "sierra": {
          "sha256": "bd606ba22bca049b7f0457cdfa846aefa09eaf2c9d1e18ff3584254e1fc05048",
          "url": "https://linuxbrew.bintray.com/bottles/privoxy-3.0.26.sierra.bottle.1.tar.gz"
        },
        "yosemite": {
          "sha256": "8a0e661df5d221ae65b6367791a923d1f2b769b0206b3fb50c1e6a84f2830d7b",
          "url": "https://linuxbrew.bintray.com/bottles/privoxy-3.0.26.yosemite.bottle.1.tar.gz"
        }
      },
      "prefix": "/home/linuxbrew/.linuxbrew",
      "rebuild": 1,
      "root_url": "https://linuxbrew.bintray.com/bottles"
    }
  },
  "build_dependencies": [
    "autoconf",
    "automake",
    "libtool"
  ],
  "caveats": null,
  "conflicts_with": [
  ],
  "dependencies": [
    "autoconf",
    "automake",
    "libtool",
    "pcre"
  ],
  "desc": "Advanced filtering web proxy",
  "full_name": "privoxy",
  "homepage": "https://www.privoxy.org/",
  "installed": [
  ],
  "keg_only": false,
  "linked_keg": null,
  "name": "privoxy",
  "oldname": null,
  "optional_dependencies": [
  ],
  "options": [
  ],
  "outdated": false,
  "pinned": false,
  "recommended_dependencies": [
  ],
  "requirements": [
  ],
  "revision": 0,
  "version_scheme": 0,
  "versions": {
    "bottle": true,
    "devel": null,
    "head": null,
    "stable": "3.0.26"
  }
}