{"name":"silk","full_name":"silk","desc":"Collection of traffic analysis tools","homepage":"https://tools.netsa.cert.org/silk/","oldname":null,"aliases":[],"versions":{"stable":"3.16.1","bottle":true,"devel":null,"head":null},"revision":0,"version_scheme":0,"installed":[],"linked_keg":null,"pinned":false,"outdated":false,"keg_only":false,"dependencies":["pkg-config","glib","libfixbuf","yaf","python@2"],"recommended_dependencies":[],"optional_dependencies":["python@2"],"build_dependencies":["pkg-config"],"conflicts_with":[],"caveats":null,"requirements":[],"options":[{"option":"--with-python@2","description":"Build with the PySiLK python interface"}],"bottle":{"stable":{"rebuild":0,"cellar":"/usr/local/Cellar","prefix":"/usr/local","root_url":"https://homebrew.bintray.com/bottles","files":{"high_sierra":{"url":"https://homebrew.bintray.com/bottles/silk-3.16.1.high_sierra.bottle.tar.gz","sha256":"88d56947e5912978cfffc9e5e421ba7b923df3128ad4c303351c1d62dc605816"},"sierra":{"url":"https://homebrew.bintray.com/bottles/silk-3.16.1.sierra.bottle.tar.gz","sha256":"fe1cb39f2915226df00b8fd321d5265eafa3a804996b4946a69a1e48de24adc5"},"el_capitan":{"url":"https://homebrew.bintray.com/bottles/silk-3.16.1.el_capitan.bottle.tar.gz","sha256":"9fa14b7dac6e5e8fcd6197cc90f581440b18ea6fa2fc35e46bd449f8f5d1f697"}}}}}