{
  "aliases": [
  ],
  "bottle": {
    "stable": {
      "cellar": ":any",
      "files": {
        "el_capitan": {
          "sha256": "6a0df3e5fb40699d9b1198562b3b3a4e1745c3a0d12923c461246b7784b8324c",
          "url": "https://linuxbrew.bintray.com/bottles/srecord-1.64.el_capitan.bottle.tar.gz"
        },
        "high_sierra": {
          "sha256": "f6341ba9022e6cbc057c519fcdc7c7518247c850025777b80d2463341315d88c",
          "url": "https://linuxbrew.bintray.com/bottles/srecord-1.64.high_sierra.bottle.tar.gz"
        },
        "mavericks": {
          "sha256": "10a04c2aca5e6f554c00aa57bd05f9c3cbe46238c9af66678dc1e6a3323c5cdb",
          "url": "https://linuxbrew.bintray.com/bottles/srecord-1.64.mavericks.bottle.tar.gz"
        },
        "sierra": {
          "sha256": "0601896fc392a13f7ef861fc3840fadfc7ddc7313763c1d374555129f4301c0d",
          "url": "https://linuxbrew.bintray.com/bottles/srecord-1.64.sierra.bottle.tar.gz"
        },
        "yosemite": {
          "sha256": "c3c29b357c44bc3da2dbb8f23a6d83aeb637aa374fe0564eb9454e5e6b53d54c",
          "url": "https://linuxbrew.bintray.com/bottles/srecord-1.64.yosemite.bottle.tar.gz"
        }
      },
      "prefix": "/home/linuxbrew/.linuxbrew",
      "rebuild": 0,
      "root_url": "https://linuxbrew.bintray.com/bottles"
    }
  },
  "build_dependencies": [
    "libtool"
  ],
  "caveats": null,
  "conflicts_with": [
  ],
  "dependencies": [
    "libtool",
    "boost",
    "libgcrypt"
  ],
  "desc": "Tools for manipulating EPROM load files",
  "full_name": "srecord",
  "homepage": "https://srecord.sourceforge.io/",
  "installed": [
  ],
  "keg_only": false,
  "linked_keg": null,
  "name": "srecord",
  "oldname": null,
  "optional_dependencies": [
  ],
  "options": [
  ],
  "outdated": false,
  "pinned": false,
  "recommended_dependencies": [
  ],
  "requirements": [
  ],
  "revision": 0,
  "version_scheme": 0,
  "versions": {
    "bottle": true,
    "devel": null,
    "head": null,
    "stable": "1.64"
  }
}