{"name":"urh","full_name":"urh","desc":"Universal Radio Hacker","homepage":"https://github.com/jopohl/urh","oldname":null,"aliases":[],"versions":{"stable":"2.0.0","bottle":true,"devel":null,"head":"HEAD"},"revision":2,"version_scheme":0,"installed":[],"linked_keg":null,"pinned":false,"outdated":false,"keg_only":false,"dependencies":["pkg-config","python","pyqt","zeromq","hackrf"],"recommended_dependencies":[],"optional_dependencies":["hackrf"],"build_dependencies":["pkg-config"],"conflicts_with":[],"caveats":null,"requirements":[],"options":[{"option":"--with-hackrf","description":"Build with libhackrf support"}],"bottle":{"stable":{"rebuild":0,"cellar":"/usr/local/Cellar","prefix":"/usr/local","root_url":"https://homebrew.bintray.com/bottles","files":{"high_sierra":{"url":"https://homebrew.bintray.com/bottles/urh-2.0.0_2.high_sierra.bottle.tar.gz","sha256":"a74135ac416c46a23ec7e1734ebbb9ef21420e4b0a78dc82fec96710a4ca058c"},"sierra":{"url":"https://homebrew.bintray.com/bottles/urh-2.0.0_2.sierra.bottle.tar.gz","sha256":"ef6181af8760e1a4216e1e36bc17222459f9cfe60dee1c3a4ef4a6e6a07b13af"},"el_capitan":{"url":"https://homebrew.bintray.com/bottles/urh-2.0.0_2.el_capitan.bottle.tar.gz","sha256":"67e8c523afb36c18abf688c3de5c3ee2d2c9a81cfd0c5fcf2993a466c86ab1b0"}}}}}